sammhelper/MonteCarlo.py
sammhelper/PID_controller.py
sammhelper/__init__.py
sammhelper/curve_fit.py
sammhelper/curve_fit_ode.py
sammhelper/data_import.py
sammhelper/delay.py
sammhelper/fft.py
sammhelper/fill_array.py
sammhelper/get_index.py
sammhelper/greet.py
sammhelper/len_check.py
sammhelper/limit.py
sammhelper/nextprime.py
sammhelper/proprint.py
sammhelper/sensitivity.py
sammhelper/sol_ode.py
sammhelper/two_pos_controller.py
sammhelper/two_position.py
sammhelper/version.py
sammhelper/.idea/misc.xml
sammhelper/.idea/modules.xml
sammhelper/.idea/sammhelper.iml
sammhelper/.idea/vcs.xml
sammhelper/.idea/workspace.xml
sammhelper/.idea/inspectionProfiles/profiles_settings.xml
sammhelper-0.3.14.dist-info/METADATA
sammhelper-0.3.14.dist-info/WHEEL
sammhelper-0.3.14.dist-info/licenses/LICENSE
sammhelper-0.3.14.dist-info/RECORD
