Metadata-Version: 2.4
Name: sammhelper
Version: 0.3.14
Summary: Supports mathematical modeling in the field of urban water management
Author-email: "Chairs of Urban Water Management (ETH Zurich)" <sww@ifu.baug.ethz.ch>
License: Copyright (c) 2018 The Python Packaging Authority
License-File: LICENSE
Classifier: License :: OSI Approved :: MIT License
Classifier: Operating System :: OS Independent
Classifier: Programming Language :: Python :: 3
Requires-Python: >=3.7
